Metadata-Version: 2.1
Name: autothread
Version: 0.0.10
Home-page: https://github.com/Basdbruijne/autothread
Author: Bas de Bruijne
Author-email: basdbruijne@gmail.com
License: MIT
Keywords: multithreading,multiprocessing,decorator
Classifier: Development Status :: 3 - Alpha
Classifier: Intended Audience :: Developers
Classifier: Topic :: Software Development :: Build Tools
Classifier: License :: OSI Approved :: MIT License
Classifier: Programming Language :: Python :: 3.7
Classifier: Programming Language :: Python :: 3.8
Classifier: Programming Language :: Python :: 3.9
Classifier: Programming Language :: Python :: 3.10
Classifier: Programming Language :: Python :: 3.11
License-File: LICENSE.txt
